pinkboto
