Metadata-Version: 2.1
Name: pinkboto
Version: 0.0.51
Summary: A Colorful AWS SDK wrapper for Python
Home-page: https://github.com/Hotmart-Org/pinkboto
Author: Jônatas Renan Camilo Alves
Author-email: jonatas.alves@hotmart.com
Keywords: aws sdk api pinkboto boto
Classifier: Development Status :: 5 - Production/Stable
Classifier: Intended Audience :: Developers
Classifier: License :: OSI Approved :: GNU General Public License v3 (GPLv3)
Classifier: Programming Language :: Python :: 3
Classifier: Topic :: Software Development :: Libraries :: Python Modules
Classifier: Topic :: Utilities
License-File: LICENSE.txt
Requires-Dist: boto3>=1.18.50
Requires-Dist: pyyaml>=5.1
Requires-Dist: Jinja2<3.2.0,>=2.10.1
Requires-Dist: python-json-logger==2.0.4
